ggtools/__init__.py
ggtools/gg/__init__.py
ggtools/gg/ddk_gaussian.py
ggtools/gg/filter.py
ggtools/gg/fit_func.py
ggtools/gg/gldas_utils.py
ggtools/gg/gsm_utils.py
ggtools/gg/landmask.py
ggtools/gg/lcurve.py
ggtools/gg/leakage.py
ggtools/gg/lovenums.py
ggtools/gg/lsm.py
ggtools/gg/lsq.py
ggtools/gg/mascon.py
ggtools/gg/plot.py
ggtools/gg/regular_gldas.py
ggtools/gg/slr_utils.py
ggtools/gg/static_models.py
ggtools/gg/utils.py
ggtools/gg/DDK_filter/__init__.py
ggtools/gg/DDK_filter/filterSH.py
ggtools/gg/DDK_filter/read_BIN.py
ggtools/ggclasses/__init__.py
ggtools/ggclasses/class_GLDAS.py
ggtools/ggclasses/class_GSM.py
ggtools/ggclasses/class_Grid.py
ggtools/ggclasses/class_Mascon.py
ggtools/ggclasses/class_Nodes.py
ggtools/ggclasses/class_SLR_C20.py
ggtools/ggclasses/class_Series.py
ggtools-1.1.7.dist-info/LICENSE.txt
ggtools-1.1.7.dist-info/METADATA
ggtools-1.1.7.dist-info/WHEEL
ggtools-1.1.7.dist-info/top_level.txt
ggtools-1.1.7.dist-info/RECORD
