Metadata-Version: 2.1
Name: ggtools
Version: 1.1.7
Summary: A package to handle the GRACE and GRACE-FO GSM data and GLDAS grid data
Home-page: https://github.com/lcx366/GGTOOLS
Author: Chunxiao Li
Author-email: lcx366@126.com
License: MIT
Platform: UNKNOWN
Classifier: Intended Audience :: Education
Classifier: Intended Audience :: Science/Research
Classifier: Programming Language :: Python :: 3.7
Classifier: License :: OSI Approved :: MIT License
Requires-Dist: scipy
Requires-Dist: numpy
Requires-Dist: matplotlib
Requires-Dist: pyshtools (>=4.6.2)
Requires-Dist: GPy
Requires-Dist: xarray
Requires-Dist: requests
Requires-Dist: astropy
Requires-Dist: sphericalpolygon
Requires-Dist: datetime
